parquetdb/__init__.py
parquetdb/_version.py
parquetdb/core/__init__.py
parquetdb/core/parquetdb.py
parquetdb/core/types.py
parquetdb/graph/__init__.py
parquetdb/graph/edges.py
parquetdb/graph/generator_store.py
parquetdb/graph/nodes.py
parquetdb/graph/parquet_graphdb.py
parquetdb/graph/utils.py
parquetdb/utils/__init__.py
parquetdb/utils/config.py
parquetdb/utils/config.yml
parquetdb/utils/data_utils.py
parquetdb/utils/external_utils.py
parquetdb/utils/general_utils.py
parquetdb/utils/log_utils.py
parquetdb/utils/matplotlib_utils.py
parquetdb/utils/mp_utils.py
parquetdb/utils/plot_utils.py
parquetdb/utils/pyarrow_utils.py
parquetdb-1.0.1.dist-info/licenses/LICENSE
parquetdb-1.0.1.dist-info/METADATA
parquetdb-1.0.1.dist-info/WHEEL
parquetdb-1.0.1.dist-info/top_level.txt
parquetdb-1.0.1.dist-info/RECORD
