Metadata-Version: 2.4
Name: parquetdb
Version: 1.0.1
Summary: ParquetDB is a lightweight database-like system built on top of Apache Parquet files using PyArrow.
Author-email: Logan Lang <lllang@mix.wvu.edu>, Aldo Romero <Aldo.Romero@mail.wvu.edu>, Kamal Choudhary <kamal.choudhary@nist.gov>, Eduardo Hernandez <Eduardo.Hernandez@csic.es>
License: MIT License
Project-URL: Repository, https://github.com/romerogroup/ParquetDB
Project-URL: Issues, https://github.com/romerogroup/ParquetDB/issues
Project-URL: Changelog, https://github.com/romerogroup/ParquetDB/CHANGELOG.md
Keywords: parquet,pyarrow,data,storage,schema evolution,nested and complex data types,scalable,database,python
Classifier: Programming Language :: Python :: 3
Requires-Python: >=3.8
License-File: LICENSE
Requires-Dist: python-dotenv
Requires-Dist: pyarrow>=17.0.0
Requires-Dist: pandas
Requires-Dist: variconfig
Requires-Dist: matplotlib
Requires-Dist: beautifulsoup4
Requires-Dist: requests
Requires-Dist: dill
Requires-Dist: pathos
Requires-Dist: dask
Requires-Dist: distributed
Requires-Dist: platformdirs
Provides-Extra: tests
Requires-Dist: pytest; extra == "tests"
Requires-Dist: pytest-cov; extra == "tests"
Provides-Extra: docs
Requires-Dist: ipython; extra == "docs"
Requires-Dist: imageio-ffmpeg; extra == "docs"
Requires-Dist: sphinx; extra == "docs"
Requires-Dist: myst_parser; extra == "docs"
Requires-Dist: sphinx_rtd_theme; extra == "docs"
Requires-Dist: sphinx-copybutton; extra == "docs"
Requires-Dist: nbsphinx; extra == "docs"
Requires-Dist: sphinx_design; extra == "docs"
Requires-Dist: sphinx-new-tab-link; extra == "docs"
Requires-Dist: sphinxcontrib-youtube; extra == "docs"
Requires-Dist: sphinxcontrib-video; extra == "docs"
Requires-Dist: pandoc; extra == "docs"
Requires-Dist: furo; extra == "docs"
Requires-Dist: numpydoc; extra == "docs"
Provides-Extra: dev
Requires-Dist: parquetdb[docs,tests]; extra == "dev"
Dynamic: license-file
